cost_tracker/__init__.py
cost_tracker/cli_tracker.py
cost_tracker/openai_token_prices.py
cost_tracker/tracker.py
openai_request_tracker-0.1.1.dist-info/LICENSE
openai_request_tracker-0.1.1.dist-info/METADATA
openai_request_tracker-0.1.1.dist-info/WHEEL
openai_request_tracker-0.1.1.dist-info/entry_points.txt
openai_request_tracker-0.1.1.dist-info/RECORD
