Metadata-Version: 2.1
Name: openai-request-tracker
Version: 0.1.1
Summary: OpenAI cost tracker that logs OpenAI requests using opentelemetry
Home-page: https://github.com/sebastianschramm/openai-cost-tracker
Author: Sebastian Schramm
Author-email: schrammsm@gmail.com
Requires-Python: >=3.11,<4.0
Classifier: Programming Language :: Python :: 3
Classifier: Programming Language :: Python :: 3.11
Classifier: Programming Language :: Python :: 3.12
Classifier: Programming Language :: Python :: 3.13
Requires-Dist: click (>=8.1.7,<9.0.0)
Requires-Dist: openai (>=1.51.2,<2.0.0)
Requires-Dist: opentelemetry-api (>=1.27.0,<2.0.0)
Requires-Dist: opentelemetry-instrumentation-openai (>=0.33.0,<0.34.0)
Requires-Dist: opentelemetry-sdk (>=1.27.0,<2.0.0)
Project-URL: Bug Tracker, https://github.com/sebastianschramm/openai-cost-tracker/issues
Project-URL: Repository, https://github.com/sebastianschramm/openai-cost-tracker
Project-URL: Releases, https://github.com/sebastianschramm/openai-cost-tracker/releases
